AUTHORS.txt
LICENSE.txt
MANIFEST.in
README.md
setup.py
django_infuse.egg-info/PKG-INFO
django_infuse.egg-info/SOURCES.txt
django_infuse.egg-info/dependency_links.txt
django_infuse.egg-info/not-zip-safe
django_infuse.egg-info/top_level.txt
infuse/__init__.py
infuse/auth/__init__.py
infuse/auth/decorators.py
infuse/auth/permissions.py
infuse/wizard/__init__.py
infuse/wizard/mixins.py